py_the_news_api-0.1.0.dist-info/licenses/LICENSE.md
the_news_api/__init__.py
the_news_api/client.py
the_news_api/models.py
py_the_news_api-0.1.0.dist-info/METADATA
py_the_news_api-0.1.0.dist-info/WHEEL
py_the_news_api-0.1.0.dist-info/top_level.txt
py_the_news_api-0.1.0.dist-info/RECORD
