Metadata-Version: 2.4
Name: py-the-news-api
Version: 0.1.0
Summary: A Python wrapper for The News API.
Requires-Python: >=3.12
License-File: LICENSE.md
Requires-Dist: httpx
Requires-Dist: pydantic
Dynamic: license-file
